setuptools_scm_azure_pipelines/__init__.py
setuptools_scm_azure_pipelines-0.1.0.dist-info/LICENSE
setuptools_scm_azure_pipelines-0.1.0.dist-info/METADATA
setuptools_scm_azure_pipelines-0.1.0.dist-info/WHEEL
setuptools_scm_azure_pipelines-0.1.0.dist-info/entry_points.txt
setuptools_scm_azure_pipelines-0.1.0.dist-info/top_level.txt
setuptools_scm_azure_pipelines-0.1.0.dist-info/zip-safe
setuptools_scm_azure_pipelines-0.1.0.dist-info/RECORD
